bot_vk/__init__.py
bot_vk/bot_longpoll.py
bot_vk/bot_python.py
bot_vk/chat_bot.py
bot_vk/keyboard_for_bot.py
bot_vk/music.py
bot_vk-1.5.dist-info/LICENSE.txt
bot_vk-1.5.dist-info/METADATA
bot_vk-1.5.dist-info/WHEEL
bot_vk-1.5.dist-info/top_level.txt
bot_vk-1.5.dist-info/RECORD
