Metadata-Version: 2.1
Name: bot-vk
Version: 1.5
Summary: Легкое создание чат-ботов вк
Home-page: https://vk.com/@bot_vk_python-doc-1-0
Author: ivan martemyanov
Author-email: imartemy152@gmail.com
License: MIT
Keywords: vk,vk_api,vk_bot,bot_vk
Platform: UNKNOWN
Classifier: Development Status :: 3 - Alpha
Classifier: License :: OSI Approved :: MIT License
Classifier: Programming Language :: Python :: 3.6
Classifier: Topic :: Text Processing :: Linguistic
Requires-Dist: vk-api
Requires-Dist: requests
Requires-Dist: datetime
Requires-Dist: lxml
